fluke_thermal_reader/__init__.py
fluke_thermal_reader/cli.py
fluke_thermal_reader/models.py
fluke_thermal_reader/parsers.py
fluke_thermal_reader/reader.py
fluke_thermal_reader-0.1.1.dist-info/METADATA
fluke_thermal_reader-0.1.1.dist-info/WHEEL
fluke_thermal_reader-0.1.1.dist-info/top_level.txt
fluke_thermal_reader-0.1.1.dist-info/RECORD
