Metadata-Version: 2.4
Name: fluke_thermal_reader
Version: 0.1.1
Summary: Libreria Python per leggere file termografici Fluke (.is2 e .is3)
Author-email: Lorenzo Ghidini <lorigh46@gmail.com>
Project-URL: Homepage, https://github.com/LoriGH25/FlukeReader_Python
Project-URL: Repository, https://github.com/LoriGH25/FlukeReader_Python
Project-URL: Issues, https://github.com/LoriGH25/FlukeReader_Python/issues
Keywords: fluke,thermal,thermography,is2,is3,temperature
Classifier: Development Status :: 3 - Alpha
Classifier: Intended Audience :: Science/Research
Classifier: Operating System :: OS Independent
Classifier: Programming Language :: Python :: 3
Classifier: Programming Language :: Python :: 3.8
Classifier: Programming Language :: Python :: 3.9
Classifier: Programming Language :: Python :: 3.10
Classifier: Programming Language :: Python :: 3.11
Classifier: Programming Language :: Python :: 3.12
Classifier: Topic :: Scientific/Engineering :: Physics
Classifier: Topic :: Scientific/Engineering :: Image Processing
Requires-Python: >=3.8
Requires-Dist: numpy>=1.20.0
Provides-Extra: dev
Requires-Dist: pytest>=6.0; extra == "dev"
Requires-Dist: pytest-cov; extra == "dev"
Requires-Dist: black; extra == "dev"
Requires-Dist: flake8; extra == "dev"
Requires-Dist: mypy; extra == "dev"
Provides-Extra: docs
Requires-Dist: sphinx; extra == "docs"
Requires-Dist: sphinx-rtd-theme; extra == "docs"
